aiosignalrcore/__init__.py
aiosignalrcore/helpers.py
aiosignalrcore/hub/__init__.py
aiosignalrcore/hub/auth_hub_connection.py
aiosignalrcore/hub/base_hub_connection.py
aiosignalrcore/hub/errors.py
aiosignalrcore/hub/handlers.py
aiosignalrcore/hub_connection_builder.py
aiosignalrcore/messages/__init__.py
aiosignalrcore/messages/base_message.py
aiosignalrcore/messages/cancel_invocation_message.py
aiosignalrcore/messages/close_message.py
aiosignalrcore/messages/completion_message.py
aiosignalrcore/messages/handshake/__init__.py
aiosignalrcore/messages/handshake/request.py
aiosignalrcore/messages/handshake/response.py
aiosignalrcore/messages/invocation_message.py
aiosignalrcore/messages/message_type.py
aiosignalrcore/messages/ping_message.py
aiosignalrcore/messages/stream_invocation_message.py
aiosignalrcore/messages/stream_item_message.py
aiosignalrcore/protocol/__init__.py
aiosignalrcore/protocol/base_hub_protocol.py
aiosignalrcore/protocol/handshake/__init__.py
aiosignalrcore/protocol/json_hub_protocol.py
aiosignalrcore/protocol/messagepack_protocol.py
aiosignalrcore/subject.py
aiosignalrcore/transport/__init__.py
aiosignalrcore/transport/base_transport.py
aiosignalrcore/transport/websockets/__init__.py
aiosignalrcore/transport/websockets/connection.py
aiosignalrcore/transport/websockets/reconnection.py
aiosignalrcore/transport/websockets/websocket_transport.py
aiosignalrcore-0.9.2.2.dist-info/LICENSE
aiosignalrcore-0.9.2.2.dist-info/WHEEL
aiosignalrcore-0.9.2.2.dist-info/METADATA
aiosignalrcore-0.9.2.2.dist-info/RECORD
